fletura/__init__.py
fletura/card.py
fletura/dock.py
fletura/neumoflet.py
fletura/paper.py
fletura/rating.py
fletura/switch.py
fletura/timeline.py
fletura-1.0.9.dist-info/LICENSE
fletura-1.0.9.dist-info/METADATA
fletura-1.0.9.dist-info/WHEEL
fletura-1.0.9.dist-info/top_level.txt
fletura-1.0.9.dist-info/RECORD
